{
    "backgroundAudio": "Resources/SoundEffects/FactoryAmbience.wav",
    "backgroundImage": "Resources/Sprites/TonyLevelFixed.dds",
    "gameObjects": [
        {
            "components": [
                {
                    "class": "Appearance",
                    "constructors": [
                        "Resources/Sprites/Player1.dds",
                        6.0,
                        8.0,
                        0.0,
                        0.0,
                        1.0
                    ]
                },
                {
                    "class": "PlayerController",
                    "constructors": [
                        1
                    ]
                },
                {
                    "class": "PlayerMagnetism"
                },
                {
                    "class": "AABB",
                    "constructors": [
                        11.0,
                        16.0,
                        false
                    ]
                },
                {
                    "class": "Rigidbody"
                }
            ],
            "name": "Player Blue [130]",
            "position": [
                -261.0,
                -135.0,
                0.0
            ],
            "rotation": 0.0,
            "scale": [
                1.75,
                1.75
            ],
            "tag": "GameObject"
        },
        {
            "components": [
                {
                    "class": "Appearance",
                    "constructors": [
                        "Resources/Sprites/Player2.dds",
                        6.0,
                        8.0,
                        0.0,
                        0.0,
                        1.0
                    ]
                },
                {
                    "class": "PlayerController",
                    "constructors": [
                        2
                    ]
                },
                {
                    "class": "AABB",
                    "constructors": [
                        11.0,
                        16.0,
                        false
                    ]
                },
                {
                    "class": "Rigidbody"
                },
                {
                    "class": "PlayerMagnetism"
                }
            ],
            "name": "Player Red [131]",
            "position": [
                -225.0,
                -135.0,
                0.0
            ],
            "rotation": 0.0,
            "scale": [
                1.75,
                1.75
            ],
            "tag": "GameObject"
        },
        {
            "components": [
                {
                    "class": "Appearance",
                    "constructors": [
                        "Resources/Sprites/Door.dds",
                        1.0,
                        1.0,
                        0.0,
                        0.0,
                        1.0
                    ]
                },
                {
                    "class": "DoorComponent",
                    "constructors": [
                        false
                    ]
                },
                {
                    "class": "AABB",
                    "constructors": [
                        16.0,
                        32.0,
                        false
                    ]
                }
            ],
            "name": "Door [164]",
            "position": [
                225.0,
                -153.0,
                0.0
            ],
            "rotation": 0.0,
            "scale": [
                1.0,
                1.0
            ],
            "tag": "GameObject"
        },
        {
            "components": [
                {
                    "class": "Appearance",
                    "constructors": [
                        "Resources/Sprites/Gold Goal.dds",
                        1.0,
                        6.0,
                        0.0,
                        0.0,
                        1.0
                    ]
                },
                {
                    "class": "Goal",
                    "constructors": [
                        ""
                    ]
                },
                {
                    "class": "AABB",
                    "constructors": [
                        36.0,
                        36.0,
                        true
                    ]
                }
            ],
            "name": "Goal [165]",
            "position": [
                279.0,
                -153.0,
                0.0
            ],
            "rotation": 0.0,
            "scale": [
                0.25,
                0.25
            ],
            "tag": "GameObject"
        },
        {
            "components": [
                {
                    "class": "Appearance",
                    "constructors": [
                        "Resources/Sprites/PressurePlate.dds",
                        1.0,
                        1.0,
                        0.0,
                        0.0,
                        1.0
                    ]
                },
                {
                    "class": "PressurePlateComponent",
                    "constructors": [
                        1,
                        "Door [164]"
                    ]
                },
                {
                    "class": "AABB",
                    "constructors": [
                        18.0,
                        5.0,
                        true
                    ]
                }
            ],
            "name": "Pressure Plate [167]",
            "position": [
                45.0,
                -117.0,
                0.0
            ],
            "rotation": 0.0,
            "scale": [
                1.0,
                1.0
            ],
            "tag": "GameObject"
        },
        {
            "components": [
                {
                    "class": "Appearance",
                    "constructors": [
                        "Resources/Sprites/Box.dds",
                        1.0,
                        1.0,
                        0.0,
                        0.0,
                        1.0
                    ]
                },
                {
                    "class": "MagnetBox"
                },
                {
                    "class": "AABB",
                    "constructors": [
                        18.0,
                        18.0,
                        false
                    ]
                },
                {
                    "class": "Rigidbody"
                }
            ],
            "name": "Box [168]",
            "position": [
                63.0,
                99.0,
                0.0
            ],
            "rotation": 0.0,
            "scale": [
                1.0,
                1.0
            ],
            "tag": "GameObject"
        }
    ],
    "sceneID": 4,
    "stageCollision": "111111111111111111111111111111111111100000000000000000000000000000000001100000000000000000011100000000000001100000000000000000000000000000111111100000000000000000000000000000000001100000000000000111000000000000000001100000000000000000000000000000000001100000000000000000000000000000000001100001100000000000011110000000000001100000000000000000000000000000000001100000000000000000000000000000000001100000000000001111100000000000000001100000000000000000000000000000000001100000000000000000000000000000000001100000000000000000011111110000000001100000000000000000000000000000000001100000000000000000000000000000000001100000000000000000000000000000000001100000000000000000000000000000000001111111111111111111111111111111111111"
}
